{
  "data": {
    "documents": {
      "document": [
        {
          "conj": {
            "+": 0,
            "-": 0
          },
          "count": {
            "punct": 1,
            "stop0": 12,
            "stop1": 7
          },
          "id": "1",
          "length": 20,
          "ner": {
            "DATE": 2,
            "PERSON": 4
          },
          "overlap": 0,
          "paragraph_id": 1,
          "paragraph_length": 6,
          "pos": {
            "punct": {
              ".": 1
            },
            "word": {
              "CD": 1,
              "DT": 1,
              "IN": 1,
              "JJ": 1,
              "NN": 2,
              "NNP": 7,
              "PRP": 1,
              "RB": 1,
              "VB": 1,
              "VBD": 2,
              "WRB": 1
            }
          },
          "position": {
            "paragraph": {
              "forward": 1,
              "reverse": 1
            },
            "sentence": {
              "document": {
                "forward": 1,
                "reverse": 6
              },
              "paragraph": {
                "forward": 1,
                "reverse": 6
              }
            }
          },
          "pronoun": {
            "personal": {
              "he": 1
            },
            "reflexive": {},
            "wh": {}
          },
          "ratio": {
            "punct": {
              "word": [
                1,
                19
              ]
            },
            "stop0": {
              "stop1": [
                12,
                7
              ]
            }
          },
          "term": {
            ".": 1,
            "2006": 1,
            "Cheney": 1,
            "Dick": 1,
            "February": 1,
            "Harry": 1,
            "President": 1,
            "Vice": 1,
            "Whittington": 1,
            "a": 1,
            "did": 1,
            "have": 1,
            "he": 1,
            "hunting": 1,
            "in": 1,
            "license": 1,
            "not": 1,
            "shot": 1,
            "valid": 1,
            "when": 1
          },
          "timex": {}
        },
        {
          "conj": {
            "+": 1,
            "-": 0
          },
          "count": {
            "punct": 1,
            "stop0": 12,
            "stop1": 11
          },
          "id": "2",
          "length": 24,
          "ner": {
            "DURATION": 2,
            "PERSON": 1
          },
          "overlap": 0,
          "paragraph_id": 1,
          "paragraph_length": 6,
          "pos": {
            "punct": {
              ".": 1
            },
            "word": {
              "CC": 1,
              "CD": 1,
              "DT": 5,
              "IN": 4,
              "NN": 5,
              "NNP": 1,
              "NNS": 1,
              "POS": 1,
              "TO": 1,
              "VBD": 1,
              "VBG": 1,
              "VBN": 1
            }
          },
          "position": {
            "paragraph": {
              "forward": 1,
              "reverse": 1
            },
            "sentence": {
              "document": {
                "forward": 2,
                "reverse": 5
              },
              "paragraph": {
                "forward": 2,
                "reverse": 5
              }
            }
          },
          "pronoun": {
            "personal": {},
            "reflexive": {},
            "wh": {}
          },
          "ratio": {
            "punct": {
              "word": [
                1,
                23
              ]
            },
            "stop0": {
              "stop1": [
                12,
                11
              ]
            }
          },
          "term": {
            "'s": 1,
            ".": 1,
            "20": 1,
            "Cheney": 1,
            "This": 1,
            "a": 1,
            "added": 1,
            "and": 1,
            "by": 2,
            "caused": 1,
            "delaying": 1,
            "for": 1,
            "hours": 1,
            "incident": 1,
            "of": 1,
            "report": 1,
            "shooting": 1,
            "staff": 1,
            "the": 3,
            "to": 1,
            "uproar": 1
          },
          "timex": {}
        },
        {
          "conj": {
            "+": 1,
            "-": 0
          },
          "count": {
            "punct": 2,
            "stop0": 13,
            "stop1": 9
          },
          "id": "3",
          "length": 24,
          "ner": {
            "LOCATION": 1,
            "PERSON": 2
          },
          "overlap": 0,
          "paragraph_id": 1,
          "paragraph_length": 6,
          "pos": {
            "punct": {
              ",": 1,
              ".": 1
            },
            "word": {
              "CC": 1,
              "DT": 2,
              "IN": 5,
              "JJ": 1,
              "NN": 6,
              "NNP": 3,
              "PRP": 1,
              "RB": 1,
              "VBD": 2
            }
          },
          "position": {
            "paragraph": {
              "forward": 1,
              "reverse": 1
            },
            "sentence": {
              "document": {
                "forward": 3,
                "reverse": 4
              },
              "paragraph": {
                "forward": 3,
                "reverse": 4
              }
            }
          },
          "pronoun": {
            "personal": {
              "they": 1
            },
            "reflexive": {},
            "wh": {}
          },
          "ratio": {
            "punct": {
              "word": [
                1,
                11
              ]
            },
            "stop0": {
              "stop1": [
                13,
                9
              ]
            }
          },
          "term": {
            ",": 1,
            ".": 1,
            "Cheney": 1,
            "Texas": 1,
            "Whittington": 1,
            "a": 1,
            "accidentally": 1,
            "and": 1,
            "bird": 1,
            "chest": 1,
            "face": 1,
            "hunted": 1,
            "in": 2,
            "neck": 1,
            "on": 1,
            "ranch": 1,
            "shot": 1,
            "south": 1,
            "sprayed": 1,
            "the": 1,
            "they": 1,
            "while": 1,
            "with": 1
          },
          "timex": {}
        },
        {
          "conj": {
            "+": 0,
            "-": 0
          },
          "count": {
            "punct": 4,
            "stop0": 15,
            "stop1": 10
          },
          "id": "4",
          "length": 29,
          "ner": {
            "NUMBER": 1,
            "PERSON": 2
          },
          "overlap": 0,
          "paragraph_id": 1,
          "paragraph_length": 6,
          "pos": {
            "punct": {
              ",": 3,
              ".": 1
            },
            "word": {
              "CD": 1,
              "DT": 3,
              "IN": 4,
              "JJ": 2,
              "NN": 5,
              "NNP": 4,
              "POS": 1,
              "TO": 1,
              "VBD": 1,
              "VBG": 1,
              "VBN": 2
            }
          },
          "position": {
            "paragraph": {
              "forward": 1,
              "reverse": 1
            },
            "sentence": {
              "document": {
                "forward": 4,
                "reverse": 3
              },
              "paragraph": {
                "forward": 4,
                "reverse": 3
              }
            }
          },
          "pronoun": {
            "personal": {},
            "reflexive": {},
            "wh": {}
          },
          "ratio": {
            "punct": {
              "word": [
                4,
                25
              ]
            },
            "stop0": {
              "stop1": [
                3,
                2
              ]
            }
          },
          "term": {
            "'s": 1,
            ",": 3,
            ".": 1,
            "78": 1,
            "Cheney": 1,
            "Christi": 1,
            "Corpus": 1,
            "Whittington": 1,
            "a": 2,
            "before": 1,
            "being": 1,
            "by": 2,
            "detail": 1,
            "helicopter": 1,
            "hospital": 1,
            "lawyer": 1,
            "medical": 1,
            "on": 1,
            "prominent": 1,
            "scene": 1,
            "taken": 1,
            "the": 1,
            "to": 1,
            "treated": 1,
            "was": 1
          },
          "timex": {}
        },
        {
          "conj": {
            "+": 0,
            "-": 0
          },
          "count": {
            "punct": 1,
            "stop0": 4,
            "stop1": 4
          },
          "id": "5",
          "length": 9,
          "ner": {
            "DATE": 3
          },
          "overlap": 0,
          "paragraph_id": 1,
          "paragraph_length": 6,
          "pos": {
            "punct": {
              ".": 1
            },
            "word": {
              "DT": 1,
              "IN": 1,
              "JJ": 2,
              "NN": 2,
              "PRP": 1,
              "VBD": 1
            }
          },
          "position": {
            "paragraph": {
              "forward": 1,
              "reverse": 1
            },
            "sentence": {
              "document": {
                "forward": 5,
                "reverse": 2
              },
              "paragraph": {
                "forward": 5,
                "reverse": 2
              }
            }
          },
          "pronoun": {
            "personal": {
              "he": 1
            },
            "reflexive": {},
            "wh": {}
          },
          "ratio": {
            "punct": {
              "word": [
                1,
                8
              ]
            },
            "stop0": {
              "stop1": [
                1,
                1
              ]
            }
          },
          "term": {
            ".": 1,
            "He": 1,
            "condition": 1,
            "day": 1,
            "in": 1,
            "next": 1,
            "stable": 1,
            "the": 1,
            "was": 1
          },
          "timex": {}
        },
        {
          "conj": {
            "+": 0,
            "-": 0
          },
          "count": {
            "punct": 1,
            "stop0": 2,
            "stop1": 1
          },
          "id": "6",
          "length": 4,
          "ner": {
            "PERSON": 1
          },
          "overlap": 0,
          "paragraph_id": 1,
          "paragraph_length": 6,
          "pos": {
            "punct": {
              ".": 1
            },
            "word": {
              "JJ": 1,
              "NNP": 1,
              "VBD": 1
            }
          },
          "position": {
            "paragraph": {
              "forward": 1,
              "reverse": 1
            },
            "sentence": {
              "document": {
                "forward": 6,
                "reverse": 1
              },
              "paragraph": {
                "forward": 6,
                "reverse": 1
              }
            }
          },
          "pronoun": {
            "personal": {},
            "reflexive": {},
            "wh": {}
          },
          "ratio": {
            "punct": {
              "word": [
                1,
                3
              ]
            },
            "stop0": {
              "stop1": [
                2,
                1
              ]
            }
          },
          "term": {
            ".": 1,
            "Cheney": 1,
            "apologetic": 1,
            "was": 1
          },
          "timex": {}
        }
      ]
    },
    "terms": {
      "term": {
        "'s": {
          "df": 2,
          "id": "'s",
          "idf": 1.0986122886681098,
          "tf": {
            "length": 6,
            "max": 1,
            "mean": 0.3333333333333333,
            "min": 0,
            "sum": 2,
            "vector": [
              0,
              1,
              0,
              1,
              0,
              0
            ]
          },
          "tfidf": {
            "length": 6,
            "max": 1.0986122886681098,
            "mean": 0.3662040962227033,
            "min": 0.0,
            "sum": 2.1972245773362196,
            "vector": [
              0.0,
              1.0986122886681098,
              0.0,
              1.0986122886681098,
              0.0,
              0.0
            ]
          }
        },
        ",": {
          "df": 2,
          "id": ",",
          "idf": 1.0986122886681098,
          "tf": {
            "length": 6,
            "max": 3,
            "mean": 0.6666666666666666,
            "min": 0,
            "sum": 4,
            "vector": [
              0,
              0,
              1,
              3,
              0,
              0
            ]
          },
          "tfidf": {
            "length": 6,
            "max": 3.295836866004329,
            "mean": 0.7324081924454066,
            "min": 0.0,
            "sum": 4.394449154672439,
            "vector": [
              0.0,
              0.0,
              1.0986122886681098,
              3.295836866004329,
              0.0,
              0.0
            ]
          }
        },
        ".": {
          "df": 6,
          "id": ".",
          "idf": 0.0,
          "tf": {
            "length": 6,
            "max": 1,
            "mean": 1.0,
            "min": 1,
            "sum": 6,
            "vector": [
              1,
              1,
              1,
              1,
              1,
              1
            ]
          },
          "tfidf": {
            "length": 6,
            "max": 0.0,
            "mean": 0.0,
            "min": 0.0,
            "sum": 0.0,
            "vector": [
              0.0,
              0.0,
              0.0,
              0.0,
              0.0,
              0.0
            ]
          }
        },
        "20": {
          "df": 1,
          "id": "20",
          "idf": 1.791759469228055,
          "tf": {
            "length": 6,
            "max": 1,
            "mean": 0.16666666666666666,
            "min": 0,
            "sum": 1,
            "vector": [
              0,
              1,
              0,
              0,
              0,
              0
            ]
          },
          "tfidf": {
            "length": 6,
            "max": 1.791759469228055,
            "mean": 0.2986265782046758,
            "min": 0.0,
            "sum": 1.791759469228055,
            "vector": [
              0.0,
              1.791759469228055,
              0.0,
              0.0,
              0.0,
              0.0
            ]
          }
        },
        "2006": {
          "df": 1,
          "id": "2006",
          "idf": 1.791759469228055,
          "tf": {
            "length": 6,
            "max": 1,
            "mean": 0.16666666666666666,
            "min": 0,
            "sum": 1,
            "vector": [
              1,
              0,
              0,
              0,
              0,
              0
            ]
          },
          "tfidf": {
            "length": 6,
            "max": 1.791759469228055,
            "mean": 0.2986265782046758,
            "min": 0.0,
            "sum": 1.791759469228055,
            "vector": [
              1.791759469228055,
              0.0,
              0.0,
              0.0,
              0.0,
              0.0
            ]
          }
        },
        "78": {
          "df": 1,
          "id": "78",
          "idf": 1.791759469228055,
          "tf": {
            "length": 6,
            "max": 1,
            "mean": 0.16666666666666666,
            "min": 0,
            "sum": 1,
            "vector": [
              0,
              0,
              0,
              1,
              0,
              0
            ]
          },
          "tfidf": {
            "length": 6,
            "max": 1.791759469228055,
            "mean": 0.2986265782046758,
            "min": 0.0,
            "sum": 1.791759469228055,
            "vector": [
              0.0,
              0.0,
              0.0,
              1.791759469228055,
              0.0,
              0.0
            ]
          }
        },
        "Cheney": {
          "df": 5,
          "id": "Cheney",
          "idf": 0.1823215567939546,
          "tf": {
            "length": 6,
            "max": 1,
            "mean": 0.8333333333333334,
            "min": 0,
            "sum": 5,
            "vector": [
              1,
              1,
              1,
              1,
              0,
              1
            ]
          },
          "tfidf": {
            "length": 6,
            "max": 0.1823215567939546,
            "mean": 0.15193463066162882,
            "min": 0.0,
            "sum": 0.9116077839697729,
            "vector": [
              0.1823215567939546,
              0.1823215567939546,
              0.1823215567939546,
              0.1823215567939546,
              0.0,
              0.1823215567939546
            ]
          }
        },
        "Christi": {
          "df": 1,
          "id": "Christi",
          "idf": 1.791759469228055,
          "tf": {
            "length": 6,
            "max": 1,
            "mean": 0.16666666666666666,
            "min": 0,
            "sum": 1,
            "vector": [
              0,
              0,
              0,
              1,
              0,
              0
            ]
          },
          "tfidf": {
            "length": 6,
            "max": 1.791759469228055,
            "mean": 0.2986265782046758,
            "min": 0.0,
            "sum": 1.791759469228055,
            "vector": [
              0.0,
              0.0,
              0.0,
              1.791759469228055,
              0.0,
              0.0
            ]
          }
        },
        "Corpus": {
          "df": 1,
          "id": "Corpus",
          "idf": 1.791759469228055,
          "tf": {
            "length": 6,
            "max": 1,
            "mean": 0.16666666666666666,
            "min": 0,
            "sum": 1,
            "vector": [
              0,
              0,
              0,
              1,
              0,
              0
            ]
          },
          "tfidf": {
            "length": 6,
            "max": 1.791759469228055,
            "mean": 0.2986265782046758,
            "min": 0.0,
            "sum": 1.791759469228055,
            "vector": [
              0.0,
              0.0,
              0.0,
              1.791759469228055,
              0.0,
              0.0
            ]
          }
        },
        "Dick": {
          "df": 1,
          "id": "Dick",
          "idf": 1.791759469228055,
          "tf": {
            "length": 6,
            "max": 1,
            "mean": 0.16666666666666666,
            "min": 0,
            "sum": 1,
            "vector": [
              1,
              0,
              0,
              0,
              0,
              0
            ]
          },
          "tfidf": {
            "length": 6,
            "max": 1.791759469228055,
            "mean": 0.2986265782046758,
            "min": 0.0,
            "sum": 1.791759469228055,
            "vector": [
              1.791759469228055,
              0.0,
              0.0,
              0.0,
              0.0,
              0.0
            ]
          }
        },
        "February": {
          "df": 1,
          "id": "February",
          "idf": 1.791759469228055,
          "tf": {
            "length": 6,
            "max": 1,
            "mean": 0.16666666666666666,
            "min": 0,
            "sum": 1,
            "vector": [
              1,
              0,
              0,
              0,
              0,
              0
            ]
          },
          "tfidf": {
            "length": 6,
            "max": 1.791759469228055,
            "mean": 0.2986265782046758,
            "min": 0.0,
            "sum": 1.791759469228055,
            "vector": [
              1.791759469228055,
              0.0,
              0.0,
              0.0,
              0.0,
              0.0
            ]
          }
        },
        "Harry": {
          "df": 1,
          "id": "Harry",
          "idf": 1.791759469228055,
          "tf": {
            "length": 6,
            "max": 1,
            "mean": 0.16666666666666666,
            "min": 0,
            "sum": 1,
            "vector": [
              1,
              0,
              0,
              0,
              0,
              0
            ]
          },
          "tfidf": {
            "length": 6,
            "max": 1.791759469228055,
            "mean": 0.2986265782046758,
            "min": 0.0,
            "sum": 1.791759469228055,
            "vector": [
              1.791759469228055,
              0.0,
              0.0,
              0.0,
              0.0,
              0.0
            ]
          }
        },
        "He": {
          "df": 1,
          "id": "He",
          "idf": 1.791759469228055,
          "tf": {
            "length": 6,
            "max": 1,
            "mean": 0.16666666666666666,
            "min": 0,
            "sum": 1,
            "vector": [
              0,
              0,
              0,
              0,
              1,
              0
            ]
          },
          "tfidf": {
            "length": 6,
            "max": 1.791759469228055,
            "mean": 0.2986265782046758,
            "min": 0.0,
            "sum": 1.791759469228055,
            "vector": [
              0.0,
              0.0,
              0.0,
              0.0,
              1.791759469228055,
              0.0
            ]
          }
        },
        "President": {
          "df": 1,
          "id": "President",
          "idf": 1.791759469228055,
          "tf": {
            "length": 6,
            "max": 1,
            "mean": 0.16666666666666666,
            "min": 0,
            "sum": 1,
            "vector": [
              1,
              0,
              0,
              0,
              0,
              0
            ]
          },
          "tfidf": {
            "length": 6,
            "max": 1.791759469228055,
            "mean": 0.2986265782046758,
            "min": 0.0,
            "sum": 1.791759469228055,
            "vector": [
              1.791759469228055,
              0.0,
              0.0,
              0.0,
              0.0,
              0.0
            ]
          }
        },
        "Texas": {
          "df": 1,
          "id": "Texas",
          "idf": 1.791759469228055,
          "tf": {
            "length": 6,
            "max": 1,
            "mean": 0.16666666666666666,
            "min": 0,
            "sum": 1,
            "vector": [
              0,
              0,
              1,
              0,
              0,
              0
            ]
          },
          "tfidf": {
            "length": 6,
            "max": 1.791759469228055,
            "mean": 0.2986265782046758,
            "min": 0.0,
            "sum": 1.791759469228055,
            "vector": [
              0.0,
              0.0,
              1.791759469228055,
              0.0,
              0.0,
              0.0
            ]
          }
        },
        "This": {
          "df": 1,
          "id": "This",
          "idf": 1.791759469228055,
          "tf": {
            "length": 6,
            "max": 1,
            "mean": 0.16666666666666666,
            "min": 0,
            "sum": 1,
            "vector": [
              0,
              1,
              0,
              0,
              0,
              0
            ]
          },
          "tfidf": {
            "length": 6,
            "max": 1.791759469228055,
            "mean": 0.2986265782046758,
            "min": 0.0,
            "sum": 1.791759469228055,
            "vector": [
              0.0,
              1.791759469228055,
              0.0,
              0.0,
              0.0,
              0.0
            ]
          }
        },
        "Vice": {
          "df": 1,
          "id": "Vice",
          "idf": 1.791759469228055,
          "tf": {
            "length": 6,
            "max": 1,
            "mean": 0.16666666666666666,
            "min": 0,
            "sum": 1,
            "vector": [
              1,
              0,
              0,
              0,
              0,
              0
            ]
          },
          "tfidf": {
            "length": 6,
            "max": 1.791759469228055,
            "mean": 0.2986265782046758,
            "min": 0.0,
            "sum": 1.791759469228055,
            "vector": [
              1.791759469228055,
              0.0,
              0.0,
              0.0,
              0.0,
              0.0
            ]
          }
        },
        "Whittington": {
          "df": 3,
          "id": "Whittington",
          "idf": 0.6931471805599453,
          "tf": {
            "length": 6,
            "max": 1,
            "mean": 0.5,
            "min": 0,
            "sum": 3,
            "vector": [
              1,
              0,
              1,
              1,
              0,
              0
            ]
          },
          "tfidf": {
            "length": 6,
            "max": 0.6931471805599453,
            "mean": 0.34657359027997264,
            "min": 0.0,
            "sum": 2.0794415416798357,
            "vector": [
              0.6931471805599453,
              0.0,
              0.6931471805599453,
              0.6931471805599453,
              0.0,
              0.0
            ]
          }
        },
        "a": {
          "df": 4,
          "id": "a",
          "idf": 0.4054651081081644,
          "tf": {
            "length": 6,
            "max": 2,
            "mean": 0.8333333333333334,
            "min": 0,
            "sum": 5,
            "vector": [
              1,
              1,
              1,
              2,
              0,
              0
            ]
          },
          "tfidf": {
            "length": 6,
            "max": 0.8109302162163288,
            "mean": 0.337887590090137,
            "min": 0.0,
            "sum": 2.027325540540822,
            "vector": [
              0.4054651081081644,
              0.4054651081081644,
              0.4054651081081644,
              0.8109302162163288,
              0.0,
              0.0
            ]
          }
        },
        "accidentally": {
          "df": 1,
          "id": "accidentally",
          "idf": 1.791759469228055,
          "tf": {
            "length": 6,
            "max": 1,
            "mean": 0.16666666666666666,
            "min": 0,
            "sum": 1,
            "vector": [
              0,
              0,
              1,
              0,
              0,
              0
            ]
          },
          "tfidf": {
            "length": 6,
            "max": 1.791759469228055,
            "mean": 0.2986265782046758,
            "min": 0.0,
            "sum": 1.791759469228055,
            "vector": [
              0.0,
              0.0,
              1.791759469228055,
              0.0,
              0.0,
              0.0
            ]
          }
        },
        "added": {
          "df": 1,
          "id": "added",
          "idf": 1.791759469228055,
          "tf": {
            "length": 6,
            "max": 1,
            "mean": 0.16666666666666666,
            "min": 0,
            "sum": 1,
            "vector": [
              0,
              1,
              0,
              0,
              0,
              0
            ]
          },
          "tfidf": {
            "length": 6,
            "max": 1.791759469228055,
            "mean": 0.2986265782046758,
            "min": 0.0,
            "sum": 1.791759469228055,
            "vector": [
              0.0,
              1.791759469228055,
              0.0,
              0.0,
              0.0,
              0.0
            ]
          }
        },
        "and": {
          "df": 2,
          "id": "and",
          "idf": 1.0986122886681098,
          "tf": {
            "length": 6,
            "max": 1,
            "mean": 0.3333333333333333,
            "min": 0,
            "sum": 2,
            "vector": [
              0,
              1,
              1,
              0,
              0,
              0
            ]
          },
          "tfidf": {
            "length": 6,
            "max": 1.0986122886681098,
            "mean": 0.3662040962227033,
            "min": 0.0,
            "sum": 2.1972245773362196,
            "vector": [
              0.0,
              1.0986122886681098,
              1.0986122886681098,
              0.0,
              0.0,
              0.0
            ]
          }
        },
        "apologetic": {
          "df": 1,
          "id": "apologetic",
          "idf": 1.791759469228055,
          "tf": {
            "length": 6,
            "max": 1,
            "mean": 0.16666666666666666,
            "min": 0,
            "sum": 1,
            "vector": [
              0,
              0,
              0,
              0,
              0,
              1
            ]
          },
          "tfidf": {
            "length": 6,
            "max": 1.791759469228055,
            "mean": 0.2986265782046758,
            "min": 0.0,
            "sum": 1.791759469228055,
            "vector": [
              0.0,
              0.0,
              0.0,
              0.0,
              0.0,
              1.791759469228055
            ]
          }
        },
        "before": {
          "df": 1,
          "id": "before",
          "idf": 1.791759469228055,
          "tf": {
            "length": 6,
            "max": 1,
            "mean": 0.16666666666666666,
            "min": 0,
            "sum": 1,
            "vector": [
              0,
              0,
              0,
              1,
              0,
              0
            ]
          },
          "tfidf": {
            "length": 6,
            "max": 1.791759469228055,
            "mean": 0.2986265782046758,
            "min": 0.0,
            "sum": 1.791759469228055,
            "vector": [
              0.0,
              0.0,
              0.0,
              1.791759469228055,
              0.0,
              0.0
            ]
          }
        },
        "being": {
          "df": 1,
          "id": "being",
          "idf": 1.791759469228055,
          "tf": {
            "length": 6,
            "max": 1,
            "mean": 0.16666666666666666,
            "min": 0,
            "sum": 1,
            "vector": [
              0,
              0,
              0,
              1,
              0,
              0
            ]
          },
          "tfidf": {
            "length": 6,
            "max": 1.791759469228055,
            "mean": 0.2986265782046758,
            "min": 0.0,
            "sum": 1.791759469228055,
            "vector": [
              0.0,
              0.0,
              0.0,
              1.791759469228055,
              0.0,
              0.0
            ]
          }
        },
        "bird": {
          "df": 1,
          "id": "bird",
          "idf": 1.791759469228055,
          "tf": {
            "length": 6,
            "max": 1,
            "mean": 0.16666666666666666,
            "min": 0,
            "sum": 1,
            "vector": [
              0,
              0,
              1,
              0,
              0,
              0
            ]
          },
          "tfidf": {
            "length": 6,
            "max": 1.791759469228055,
            "mean": 0.2986265782046758,
            "min": 0.0,
            "sum": 1.791759469228055,
            "vector": [
              0.0,
              0.0,
              1.791759469228055,
              0.0,
              0.0,
              0.0
            ]
          }
        },
        "by": {
          "df": 2,
          "id": "by",
          "idf": 1.0986122886681098,
          "tf": {
            "length": 6,
            "max": 2,
            "mean": 0.6666666666666666,
            "min": 0,
            "sum": 4,
            "vector": [
              0,
              2,
              0,
              2,
              0,
              0
            ]
          },
          "tfidf": {
            "length": 6,
            "max": 2.1972245773362196,
            "mean": 0.7324081924454066,
            "min": 0.0,
            "sum": 4.394449154672439,
            "vector": [
              0.0,
              2.1972245773362196,
              0.0,
              2.1972245773362196,
              0.0,
              0.0
            ]
          }
        },
        "caused": {
          "df": 1,
          "id": "caused",
          "idf": 1.791759469228055,
          "tf": {
            "length": 6,
            "max": 1,
            "mean": 0.16666666666666666,
            "min": 0,
            "sum": 1,
            "vector": [
              0,
              1,
              0,
              0,
              0,
              0
            ]
          },
          "tfidf": {
            "length": 6,
            "max": 1.791759469228055,
            "mean": 0.2986265782046758,
            "min": 0.0,
            "sum": 1.791759469228055,
            "vector": [
              0.0,
              1.791759469228055,
              0.0,
              0.0,
              0.0,
              0.0
            ]
          }
        },
        "chest": {
          "df": 1,
          "id": "chest",
          "idf": 1.791759469228055,
          "tf": {
            "length": 6,
            "max": 1,
            "mean": 0.16666666666666666,
            "min": 0,
            "sum": 1,
            "vector": [
              0,
              0,
              1,
              0,
              0,
              0
            ]
          },
          "tfidf": {
            "length": 6,
            "max": 1.791759469228055,
            "mean": 0.2986265782046758,
            "min": 0.0,
            "sum": 1.791759469228055,
            "vector": [
              0.0,
              0.0,
              1.791759469228055,
              0.0,
              0.0,
              0.0
            ]
          }
        },
        "condition": {
          "df": 1,
          "id": "condition",
          "idf": 1.791759469228055,
          "tf": {
            "length": 6,
            "max": 1,
            "mean": 0.16666666666666666,
            "min": 0,
            "sum": 1,
            "vector": [
              0,
              0,
              0,
              0,
              1,
              0
            ]
          },
          "tfidf": {
            "length": 6,
            "max": 1.791759469228055,
            "mean": 0.2986265782046758,
            "min": 0.0,
            "sum": 1.791759469228055,
            "vector": [
              0.0,
              0.0,
              0.0,
              0.0,
              1.791759469228055,
              0.0
            ]
          }
        },
        "day": {
          "df": 1,
          "id": "day",
          "idf": 1.791759469228055,
          "tf": {
            "length": 6,
            "max": 1,
            "mean": 0.16666666666666666,
            "min": 0,
            "sum": 1,
            "vector": [
              0,
              0,
              0,
              0,
              1,
              0
            ]
          },
          "tfidf": {
            "length": 6,
            "max": 1.791759469228055,
            "mean": 0.2986265782046758,
            "min": 0.0,
            "sum": 1.791759469228055,
            "vector": [
              0.0,
              0.0,
              0.0,
              0.0,
              1.791759469228055,
              0.0
            ]
          }
        },
        "delaying": {
          "df": 1,
          "id": "delaying",
          "idf": 1.791759469228055,
          "tf": {
            "length": 6,
            "max": 1,
            "mean": 0.16666666666666666,
            "min": 0,
            "sum": 1,
            "vector": [
              0,
              1,
              0,
              0,
              0,
              0
            ]
          },
          "tfidf": {
            "length": 6,
            "max": 1.791759469228055,
            "mean": 0.2986265782046758,
            "min": 0.0,
            "sum": 1.791759469228055,
            "vector": [
              0.0,
              1.791759469228055,
              0.0,
              0.0,
              0.0,
              0.0
            ]
          }
        },
        "detail": {
          "df": 1,
          "id": "detail",
          "idf": 1.791759469228055,
          "tf": {
            "length": 6,
            "max": 1,
            "mean": 0.16666666666666666,
            "min": 0,
            "sum": 1,
            "vector": [
              0,
              0,
              0,
              1,
              0,
              0
            ]
          },
          "tfidf": {
            "length": 6,
            "max": 1.791759469228055,
            "mean": 0.2986265782046758,
            "min": 0.0,
            "sum": 1.791759469228055,
            "vector": [
              0.0,
              0.0,
              0.0,
              1.791759469228055,
              0.0,
              0.0
            ]
          }
        },
        "did": {
          "df": 1,
          "id": "did",
          "idf": 1.791759469228055,
          "tf": {
            "length": 6,
            "max": 1,
            "mean": 0.16666666666666666,
            "min": 0,
            "sum": 1,
            "vector": [
              1,
              0,
              0,
              0,
              0,
              0
            ]
          },
          "tfidf": {
            "length": 6,
            "max": 1.791759469228055,
            "mean": 0.2986265782046758,
            "min": 0.0,
            "sum": 1.791759469228055,
            "vector": [
              1.791759469228055,
              0.0,
              0.0,
              0.0,
              0.0,
              0.0
            ]
          }
        },
        "face": {
          "df": 1,
          "id": "face",
          "idf": 1.791759469228055,
          "tf": {
            "length": 6,
            "max": 1,
            "mean": 0.16666666666666666,
            "min": 0,
            "sum": 1,
            "vector": [
              0,
              0,
              1,
              0,
              0,
              0
            ]
          },
          "tfidf": {
            "length": 6,
            "max": 1.791759469228055,
            "mean": 0.2986265782046758,
            "min": 0.0,
            "sum": 1.791759469228055,
            "vector": [
              0.0,
              0.0,
              1.791759469228055,
              0.0,
              0.0,
              0.0
            ]
          }
        },
        "for": {
          "df": 1,
          "id": "for",
          "idf": 1.791759469228055,
          "tf": {
            "length": 6,
            "max": 1,
            "mean": 0.16666666666666666,
            "min": 0,
            "sum": 1,
            "vector": [
              0,
              1,
              0,
              0,
              0,
              0
            ]
          },
          "tfidf": {
            "length": 6,
            "max": 1.791759469228055,
            "mean": 0.2986265782046758,
            "min": 0.0,
            "sum": 1.791759469228055,
            "vector": [
              0.0,
              1.791759469228055,
              0.0,
              0.0,
              0.0,
              0.0
            ]
          }
        },
        "have": {
          "df": 1,
          "id": "have",
          "idf": 1.791759469228055,
          "tf": {
            "length": 6,
            "max": 1,
            "mean": 0.16666666666666666,
            "min": 0,
            "sum": 1,
            "vector": [
              1,
              0,
              0,
              0,
              0,
              0
            ]
          },
          "tfidf": {
            "length": 6,
            "max": 1.791759469228055,
            "mean": 0.2986265782046758,
            "min": 0.0,
            "sum": 1.791759469228055,
            "vector": [
              1.791759469228055,
              0.0,
              0.0,
              0.0,
              0.0,
              0.0
            ]
          }
        },
        "he": {
          "df": 1,
          "id": "he",
          "idf": 1.791759469228055,
          "tf": {
            "length": 6,
            "max": 1,
            "mean": 0.16666666666666666,
            "min": 0,
            "sum": 1,
            "vector": [
              1,
              0,
              0,
              0,
              0,
              0
            ]
          },
          "tfidf": {
            "length": 6,
            "max": 1.791759469228055,
            "mean": 0.2986265782046758,
            "min": 0.0,
            "sum": 1.791759469228055,
            "vector": [
              1.791759469228055,
              0.0,
              0.0,
              0.0,
              0.0,
              0.0
            ]
          }
        },
        "helicopter": {
          "df": 1,
          "id": "helicopter",
          "idf": 1.791759469228055,
          "tf": {
            "length": 6,
            "max": 1,
            "mean": 0.16666666666666666,
            "min": 0,
            "sum": 1,
            "vector": [
              0,
              0,
              0,
              1,
              0,
              0
            ]
          },
          "tfidf": {
            "length": 6,
            "max": 1.791759469228055,
            "mean": 0.2986265782046758,
            "min": 0.0,
            "sum": 1.791759469228055,
            "vector": [
              0.0,
              0.0,
              0.0,
              1.791759469228055,
              0.0,
              0.0
            ]
          }
        },
        "hospital": {
          "df": 1,
          "id": "hospital",
          "idf": 1.791759469228055,
          "tf": {
            "length": 6,
            "max": 1,
            "mean": 0.16666666666666666,
            "min": 0,
            "sum": 1,
            "vector": [
              0,
              0,
              0,
              1,
              0,
              0
            ]
          },
          "tfidf": {
            "length": 6,
            "max": 1.791759469228055,
            "mean": 0.2986265782046758,
            "min": 0.0,
            "sum": 1.791759469228055,
            "vector": [
              0.0,
              0.0,
              0.0,
              1.791759469228055,
              0.0,
              0.0
            ]
          }
        },
        "hours": {
          "df": 1,
          "id": "hours",
          "idf": 1.791759469228055,
          "tf": {
            "length": 6,
            "max": 1,
            "mean": 0.16666666666666666,
            "min": 0,
            "sum": 1,
            "vector": [
              0,
              1,
              0,
              0,
              0,
              0
            ]
          },
          "tfidf": {
            "length": 6,
            "max": 1.791759469228055,
            "mean": 0.2986265782046758,
            "min": 0.0,
            "sum": 1.791759469228055,
            "vector": [
              0.0,
              1.791759469228055,
              0.0,
              0.0,
              0.0,
              0.0
            ]
          }
        },
        "hunted": {
          "df": 1,
          "id": "hunted",
          "idf": 1.791759469228055,
          "tf": {
            "length": 6,
            "max": 1,
            "mean": 0.16666666666666666,
            "min": 0,
            "sum": 1,
            "vector": [
              0,
              0,
              1,
              0,
              0,
              0
            ]
          },
          "tfidf": {
            "length": 6,
            "max": 1.791759469228055,
            "mean": 0.2986265782046758,
            "min": 0.0,
            "sum": 1.791759469228055,
            "vector": [
              0.0,
              0.0,
              1.791759469228055,
              0.0,
              0.0,
              0.0
            ]
          }
        },
        "hunting": {
          "df": 1,
          "id": "hunting",
          "idf": 1.791759469228055,
          "tf": {
            "length": 6,
            "max": 1,
            "mean": 0.16666666666666666,
            "min": 0,
            "sum": 1,
            "vector": [
              1,
              0,
              0,
              0,
              0,
              0
            ]
          },
          "tfidf": {
            "length": 6,
            "max": 1.791759469228055,
            "mean": 0.2986265782046758,
            "min": 0.0,
            "sum": 1.791759469228055,
            "vector": [
              1.791759469228055,
              0.0,
              0.0,
              0.0,
              0.0,
              0.0
            ]
          }
        },
        "in": {
          "df": 3,
          "id": "in",
          "idf": 0.6931471805599453,
          "tf": {
            "length": 6,
            "max": 2,
            "mean": 0.6666666666666666,
            "min": 0,
            "sum": 4,
            "vector": [
              1,
              0,
              2,
              0,
              1,
              0
            ]
          },
          "tfidf": {
            "length": 6,
            "max": 1.3862943611198906,
            "mean": 0.46209812037329684,
            "min": 0.0,
            "sum": 2.772588722239781,
            "vector": [
              0.6931471805599453,
              0.0,
              1.3862943611198906,
              0.0,
              0.6931471805599453,
              0.0
            ]
          }
        },
        "incident": {
          "df": 1,
          "id": "incident",
          "idf": 1.791759469228055,
          "tf": {
            "length": 6,
            "max": 1,
            "mean": 0.16666666666666666,
            "min": 0,
            "sum": 1,
            "vector": [
              0,
              1,
              0,
              0,
              0,
              0
            ]
          },
          "tfidf": {
            "length": 6,
            "max": 1.791759469228055,
            "mean": 0.2986265782046758,
            "min": 0.0,
            "sum": 1.791759469228055,
            "vector": [
              0.0,
              1.791759469228055,
              0.0,
              0.0,
              0.0,
              0.0
            ]
          }
        },
        "lawyer": {
          "df": 1,
          "id": "lawyer",
          "idf": 1.791759469228055,
          "tf": {
            "length": 6,
            "max": 1,
            "mean": 0.16666666666666666,
            "min": 0,
            "sum": 1,
            "vector": [
              0,
              0,
              0,
              1,
              0,
              0
            ]
          },
          "tfidf": {
            "length": 6,
            "max": 1.791759469228055,
            "mean": 0.2986265782046758,
            "min": 0.0,
            "sum": 1.791759469228055,
            "vector": [
              0.0,
              0.0,
              0.0,
              1.791759469228055,
              0.0,
              0.0
            ]
          }
        },
        "license": {
          "df": 1,
          "id": "license",
          "idf": 1.791759469228055,
          "tf": {
            "length": 6,
            "max": 1,
            "mean": 0.16666666666666666,
            "min": 0,
            "sum": 1,
            "vector": [
              1,
              0,
              0,
              0,
              0,
              0
            ]
          },
          "tfidf": {
            "length": 6,
            "max": 1.791759469228055,
            "mean": 0.2986265782046758,
            "min": 0.0,
            "sum": 1.791759469228055,
            "vector": [
              1.791759469228055,
              0.0,
              0.0,
              0.0,
              0.0,
              0.0
            ]
          }
        },
        "medical": {
          "df": 1,
          "id": "medical",
          "idf": 1.791759469228055,
          "tf": {
            "length": 6,
            "max": 1,
            "mean": 0.16666666666666666,
            "min": 0,
            "sum": 1,
            "vector": [
              0,
              0,
              0,
              1,
              0,
              0
            ]
          },
          "tfidf": {
            "length": 6,
            "max": 1.791759469228055,
            "mean": 0.2986265782046758,
            "min": 0.0,
            "sum": 1.791759469228055,
            "vector": [
              0.0,
              0.0,
              0.0,
              1.791759469228055,
              0.0,
              0.0
            ]
          }
        },
        "neck": {
          "df": 1,
          "id": "neck",
          "idf": 1.791759469228055,
          "tf": {
            "length": 6,
            "max": 1,
            "mean": 0.16666666666666666,
            "min": 0,
            "sum": 1,
            "vector": [
              0,
              0,
              1,
              0,
              0,
              0
            ]
          },
          "tfidf": {
            "length": 6,
            "max": 1.791759469228055,
            "mean": 0.2986265782046758,
            "min": 0.0,
            "sum": 1.791759469228055,
            "vector": [
              0.0,
              0.0,
              1.791759469228055,
              0.0,
              0.0,
              0.0
            ]
          }
        },
        "next": {
          "df": 1,
          "id": "next",
          "idf": 1.791759469228055,
          "tf": {
            "length": 6,
            "max": 1,
            "mean": 0.16666666666666666,
            "min": 0,
            "sum": 1,
            "vector": [
              0,
              0,
              0,
              0,
              1,
              0
            ]
          },
          "tfidf": {
            "length": 6,
            "max": 1.791759469228055,
            "mean": 0.2986265782046758,
            "min": 0.0,
            "sum": 1.791759469228055,
            "vector": [
              0.0,
              0.0,
              0.0,
              0.0,
              1.791759469228055,
              0.0
            ]
          }
        },
        "not": {
          "df": 1,
          "id": "not",
          "idf": 1.791759469228055,
          "tf": {
            "length": 6,
            "max": 1,
            "mean": 0.16666666666666666,
            "min": 0,
            "sum": 1,
            "vector": [
              1,
              0,
              0,
              0,
              0,
              0
            ]
          },
          "tfidf": {
            "length": 6,
            "max": 1.791759469228055,
            "mean": 0.2986265782046758,
            "min": 0.0,
            "sum": 1.791759469228055,
            "vector": [
              1.791759469228055,
              0.0,
              0.0,
              0.0,
              0.0,
              0.0
            ]
          }
        },
        "of": {
          "df": 1,
          "id": "of",
          "idf": 1.791759469228055,
          "tf": {
            "length": 6,
            "max": 1,
            "mean": 0.16666666666666666,
            "min": 0,
            "sum": 1,
            "vector": [
              0,
              1,
              0,
              0,
              0,
              0
            ]
          },
          "tfidf": {
            "length": 6,
            "max": 1.791759469228055,
            "mean": 0.2986265782046758,
            "min": 0.0,
            "sum": 1.791759469228055,
            "vector": [
              0.0,
              1.791759469228055,
              0.0,
              0.0,
              0.0,
              0.0
            ]
          }
        },
        "on": {
          "df": 2,
          "id": "on",
          "idf": 1.0986122886681098,
          "tf": {
            "length": 6,
            "max": 1,
            "mean": 0.3333333333333333,
            "min": 0,
            "sum": 2,
            "vector": [
              0,
              0,
              1,
              1,
              0,
              0
            ]
          },
          "tfidf": {
            "length": 6,
            "max": 1.0986122886681098,
            "mean": 0.3662040962227033,
            "min": 0.0,
            "sum": 2.1972245773362196,
            "vector": [
              0.0,
              0.0,
              1.0986122886681098,
              1.0986122886681098,
              0.0,
              0.0
            ]
          }
        },
        "prominent": {
          "df": 1,
          "id": "prominent",
          "idf": 1.791759469228055,
          "tf": {
            "length": 6,
            "max": 1,
            "mean": 0.16666666666666666,
            "min": 0,
            "sum": 1,
            "vector": [
              0,
              0,
              0,
              1,
              0,
              0
            ]
          },
          "tfidf": {
            "length": 6,
            "max": 1.791759469228055,
            "mean": 0.2986265782046758,
            "min": 0.0,
            "sum": 1.791759469228055,
            "vector": [
              0.0,
              0.0,
              0.0,
              1.791759469228055,
              0.0,
              0.0
            ]
          }
        },
        "ranch": {
          "df": 1,
          "id": "ranch",
          "idf": 1.791759469228055,
          "tf": {
            "length": 6,
            "max": 1,
            "mean": 0.16666666666666666,
            "min": 0,
            "sum": 1,
            "vector": [
              0,
              0,
              1,
              0,
              0,
              0
            ]
          },
          "tfidf": {
            "length": 6,
            "max": 1.791759469228055,
            "mean": 0.2986265782046758,
            "min": 0.0,
            "sum": 1.791759469228055,
            "vector": [
              0.0,
              0.0,
              1.791759469228055,
              0.0,
              0.0,
              0.0
            ]
          }
        },
        "report": {
          "df": 1,
          "id": "report",
          "idf": 1.791759469228055,
          "tf": {
            "length": 6,
            "max": 1,
            "mean": 0.16666666666666666,
            "min": 0,
            "sum": 1,
            "vector": [
              0,
              1,
              0,
              0,
              0,
              0
            ]
          },
          "tfidf": {
            "length": 6,
            "max": 1.791759469228055,
            "mean": 0.2986265782046758,
            "min": 0.0,
            "sum": 1.791759469228055,
            "vector": [
              0.0,
              1.791759469228055,
              0.0,
              0.0,
              0.0,
              0.0
            ]
          }
        },
        "scene": {
          "df": 1,
          "id": "scene",
          "idf": 1.791759469228055,
          "tf": {
            "length": 6,
            "max": 1,
            "mean": 0.16666666666666666,
            "min": 0,
            "sum": 1,
            "vector": [
              0,
              0,
              0,
              1,
              0,
              0
            ]
          },
          "tfidf": {
            "length": 6,
            "max": 1.791759469228055,
            "mean": 0.2986265782046758,
            "min": 0.0,
            "sum": 1.791759469228055,
            "vector": [
              0.0,
              0.0,
              0.0,
              1.791759469228055,
              0.0,
              0.0
            ]
          }
        },
        "shooting": {
          "df": 1,
          "id": "shooting",
          "idf": 1.791759469228055,
          "tf": {
            "length": 6,
            "max": 1,
            "mean": 0.16666666666666666,
            "min": 0,
            "sum": 1,
            "vector": [
              0,
              1,
              0,
              0,
              0,
              0
            ]
          },
          "tfidf": {
            "length": 6,
            "max": 1.791759469228055,
            "mean": 0.2986265782046758,
            "min": 0.0,
            "sum": 1.791759469228055,
            "vector": [
              0.0,
              1.791759469228055,
              0.0,
              0.0,
              0.0,
              0.0
            ]
          }
        },
        "shot": {
          "df": 2,
          "id": "shot",
          "idf": 1.0986122886681098,
          "tf": {
            "length": 6,
            "max": 1,
            "mean": 0.3333333333333333,
            "min": 0,
            "sum": 2,
            "vector": [
              1,
              0,
              1,
              0,
              0,
              0
            ]
          },
          "tfidf": {
            "length": 6,
            "max": 1.0986122886681098,
            "mean": 0.3662040962227033,
            "min": 0.0,
            "sum": 2.1972245773362196,
            "vector": [
              1.0986122886681098,
              0.0,
              1.0986122886681098,
              0.0,
              0.0,
              0.0
            ]
          }
        },
        "south": {
          "df": 1,
          "id": "south",
          "idf": 1.791759469228055,
          "tf": {
            "length": 6,
            "max": 1,
            "mean": 0.16666666666666666,
            "min": 0,
            "sum": 1,
            "vector": [
              0,
              0,
              1,
              0,
              0,
              0
            ]
          },
          "tfidf": {
            "length": 6,
            "max": 1.791759469228055,
            "mean": 0.2986265782046758,
            "min": 0.0,
            "sum": 1.791759469228055,
            "vector": [
              0.0,
              0.0,
              1.791759469228055,
              0.0,
              0.0,
              0.0
            ]
          }
        },
        "sprayed": {
          "df": 1,
          "id": "sprayed",
          "idf": 1.791759469228055,
          "tf": {
            "length": 6,
            "max": 1,
            "mean": 0.16666666666666666,
            "min": 0,
            "sum": 1,
            "vector": [
              0,
              0,
              1,
              0,
              0,
              0
            ]
          },
          "tfidf": {
            "length": 6,
            "max": 1.791759469228055,
            "mean": 0.2986265782046758,
            "min": 0.0,
            "sum": 1.791759469228055,
            "vector": [
              0.0,
              0.0,
              1.791759469228055,
              0.0,
              0.0,
              0.0
            ]
          }
        },
        "stable": {
          "df": 1,
          "id": "stable",
          "idf": 1.791759469228055,
          "tf": {
            "length": 6,
            "max": 1,
            "mean": 0.16666666666666666,
            "min": 0,
            "sum": 1,
            "vector": [
              0,
              0,
              0,
              0,
              1,
              0
            ]
          },
          "tfidf": {
            "length": 6,
            "max": 1.791759469228055,
            "mean": 0.2986265782046758,
            "min": 0.0,
            "sum": 1.791759469228055,
            "vector": [
              0.0,
              0.0,
              0.0,
              0.0,
              1.791759469228055,
              0.0
            ]
          }
        },
        "staff": {
          "df": 1,
          "id": "staff",
          "idf": 1.791759469228055,
          "tf": {
            "length": 6,
            "max": 1,
            "mean": 0.16666666666666666,
            "min": 0,
            "sum": 1,
            "vector": [
              0,
              1,
              0,
              0,
              0,
              0
            ]
          },
          "tfidf": {
            "length": 6,
            "max": 1.791759469228055,
            "mean": 0.2986265782046758,
            "min": 0.0,
            "sum": 1.791759469228055,
            "vector": [
              0.0,
              1.791759469228055,
              0.0,
              0.0,
              0.0,
              0.0
            ]
          }
        },
        "taken": {
          "df": 1,
          "id": "taken",
          "idf": 1.791759469228055,
          "tf": {
            "length": 6,
            "max": 1,
            "mean": 0.16666666666666666,
            "min": 0,
            "sum": 1,
            "vector": [
              0,
              0,
              0,
              1,
              0,
              0
            ]
          },
          "tfidf": {
            "length": 6,
            "max": 1.791759469228055,
            "mean": 0.2986265782046758,
            "min": 0.0,
            "sum": 1.791759469228055,
            "vector": [
              0.0,
              0.0,
              0.0,
              1.791759469228055,
              0.0,
              0.0
            ]
          }
        },
        "the": {
          "df": 4,
          "id": "the",
          "idf": 0.4054651081081644,
          "tf": {
            "length": 6,
            "max": 3,
            "mean": 1.0,
            "min": 0,
            "sum": 6,
            "vector": [
              0,
              3,
              1,
              1,
              1,
              0
            ]
          },
          "tfidf": {
            "length": 6,
            "max": 1.2163953243244932,
            "mean": 0.40546510810816444,
            "min": 0.0,
            "sum": 2.4327906486489868,
            "vector": [
              0.0,
              1.2163953243244932,
              0.4054651081081644,
              0.4054651081081644,
              0.4054651081081644,
              0.0
            ]
          }
        },
        "they": {
          "df": 1,
          "id": "they",
          "idf": 1.791759469228055,
          "tf": {
            "length": 6,
            "max": 1,
            "mean": 0.16666666666666666,
            "min": 0,
            "sum": 1,
            "vector": [
              0,
              0,
              1,
              0,
              0,
              0
            ]
          },
          "tfidf": {
            "length": 6,
            "max": 1.791759469228055,
            "mean": 0.2986265782046758,
            "min": 0.0,
            "sum": 1.791759469228055,
            "vector": [
              0.0,
              0.0,
              1.791759469228055,
              0.0,
              0.0,
              0.0
            ]
          }
        },
        "to": {
          "df": 2,
          "id": "to",
          "idf": 1.0986122886681098,
          "tf": {
            "length": 6,
            "max": 1,
            "mean": 0.3333333333333333,
            "min": 0,
            "sum": 2,
            "vector": [
              0,
              1,
              0,
              1,
              0,
              0
            ]
          },
          "tfidf": {
            "length": 6,
            "max": 1.0986122886681098,
            "mean": 0.3662040962227033,
            "min": 0.0,
            "sum": 2.1972245773362196,
            "vector": [
              0.0,
              1.0986122886681098,
              0.0,
              1.0986122886681098,
              0.0,
              0.0
            ]
          }
        },
        "treated": {
          "df": 1,
          "id": "treated",
          "idf": 1.791759469228055,
          "tf": {
            "length": 6,
            "max": 1,
            "mean": 0.16666666666666666,
            "min": 0,
            "sum": 1,
            "vector": [
              0,
              0,
              0,
              1,
              0,
              0
            ]
          },
          "tfidf": {
            "length": 6,
            "max": 1.791759469228055,
            "mean": 0.2986265782046758,
            "min": 0.0,
            "sum": 1.791759469228055,
            "vector": [
              0.0,
              0.0,
              0.0,
              1.791759469228055,
              0.0,
              0.0
            ]
          }
        },
        "uproar": {
          "df": 1,
          "id": "uproar",
          "idf": 1.791759469228055,
          "tf": {
            "length": 6,
            "max": 1,
            "mean": 0.16666666666666666,
            "min": 0,
            "sum": 1,
            "vector": [
              0,
              1,
              0,
              0,
              0,
              0
            ]
          },
          "tfidf": {
            "length": 6,
            "max": 1.791759469228055,
            "mean": 0.2986265782046758,
            "min": 0.0,
            "sum": 1.791759469228055,
            "vector": [
              0.0,
              1.791759469228055,
              0.0,
              0.0,
              0.0,
              0.0
            ]
          }
        },
        "valid": {
          "df": 1,
          "id": "valid",
          "idf": 1.791759469228055,
          "tf": {
            "length": 6,
            "max": 1,
            "mean": 0.16666666666666666,
            "min": 0,
            "sum": 1,
            "vector": [
              1,
              0,
              0,
              0,
              0,
              0
            ]
          },
          "tfidf": {
            "length": 6,
            "max": 1.791759469228055,
            "mean": 0.2986265782046758,
            "min": 0.0,
            "sum": 1.791759469228055,
            "vector": [
              1.791759469228055,
              0.0,
              0.0,
              0.0,
              0.0,
              0.0
            ]
          }
        },
        "was": {
          "df": 3,
          "id": "was",
          "idf": 0.6931471805599453,
          "tf": {
            "length": 6,
            "max": 1,
            "mean": 0.5,
            "min": 0,
            "sum": 3,
            "vector": [
              0,
              0,
              0,
              1,
              1,
              1
            ]
          },
          "tfidf": {
            "length": 6,
            "max": 0.6931471805599453,
            "mean": 0.34657359027997264,
            "min": 0.0,
            "sum": 2.0794415416798357,
            "vector": [
              0.0,
              0.0,
              0.0,
              0.6931471805599453,
              0.6931471805599453,
              0.6931471805599453
            ]
          }
        },
        "when": {
          "df": 1,
          "id": "when",
          "idf": 1.791759469228055,
          "tf": {
            "length": 6,
            "max": 1,
            "mean": 0.16666666666666666,
            "min": 0,
            "sum": 1,
            "vector": [
              1,
              0,
              0,
              0,
              0,
              0
            ]
          },
          "tfidf": {
            "length": 6,
            "max": 1.791759469228055,
            "mean": 0.2986265782046758,
            "min": 0.0,
            "sum": 1.791759469228055,
            "vector": [
              1.791759469228055,
              0.0,
              0.0,
              0.0,
              0.0,
              0.0
            ]
          }
        },
        "while": {
          "df": 1,
          "id": "while",
          "idf": 1.791759469228055,
          "tf": {
            "length": 6,
            "max": 1,
            "mean": 0.16666666666666666,
            "min": 0,
            "sum": 1,
            "vector": [
              0,
              0,
              1,
              0,
              0,
              0
            ]
          },
          "tfidf": {
            "length": 6,
            "max": 1.791759469228055,
            "mean": 0.2986265782046758,
            "min": 0.0,
            "sum": 1.791759469228055,
            "vector": [
              0.0,
              0.0,
              1.791759469228055,
              0.0,
              0.0,
              0.0
            ]
          }
        },
        "with": {
          "df": 1,
          "id": "with",
          "idf": 1.791759469228055,
          "tf": {
            "length": 6,
            "max": 1,
            "mean": 0.16666666666666666,
            "min": 0,
            "sum": 1,
            "vector": [
              0,
              0,
              1,
              0,
              0,
              0
            ]
          },
          "tfidf": {
            "length": 6,
            "max": 1.791759469228055,
            "mean": 0.2986265782046758,
            "min": 0.0,
            "sum": 1.791759469228055,
            "vector": [
              0.0,
              0.0,
              1.791759469228055,
              0.0,
              0.0,
              0.0
            ]
          }
        }
      }
    }
  },
  "meta": {
    "document_order": {}
  }
}